{"concerte":[{"titlu":"Tilu8 ian","desc":"e ziua lui ian","prioritate":"verde","day":"8","month":"Ianuarie"},{"titlu":"Tiltu seminaar","desc":"asdasd","prioritate":"galben","day":"10","month":"Ianuarie"},{"titlu":"Titlu rosu","desc":"rosuuuu","prioritate":"rosu","day":"25","month":"Ianuarie"},{"titlu":"random","desc":"ransom 2","prioritate":"verde","day":"14","month":"Ianuarie"},{"titlu":"5co de mayo","desc":"saras","prioritate":"rosu","day":"5","month":"Martie"},{"titlu":"2 zi","desc":"iunie","prioritate":"rosu","day":"2","month":"Ianuarie"},{"titlu":"31 vineri","desc":"ian","prioritate":"verde","day":"31","month":"Ianuarie"},{"titlu":"asdasdsd","desc":"asdasda","prioritate":"verde","day":"5","month":"Februarie"},{"titlu":"asdasd","desc":"asdad","prioritate":"verde","day":"23","month":"Ianuarie"},{"titlu":"Eveniment pe 24Apr","desc":"O descriere frumoasa elocventa acestui eveniment","prioritate":"rosu","day":"24","month":"Aprilie"}]}